{"title":"Van Halen 1975-06-13 Pasadena SOUNDBOARD COVERS INCLUDED","uid":5547881,"size":93468865,"categoryP":"audio","categoryS":"other","magnet":"?xt=urn:btih:0436c6c8365dfa3134b6234ae195e24945a94662&amp;dn=Van+Halen+1975-06-13+Pasadena+SOUNDBOARD+COVERS+INCLUDED&amp;tr=udp%3A%2F%2Ftracker.openbittorrent.com%3A80&amp;tr=udp%3A%2F%2Fopen.demonii.com%3A1337&amp;tr=udp%3A%2F%2Ftracker.coppersurfer.tk%3A6969&amp;tr=udp%3A%2F%2Fexodus.desync.com%3A6969","seeders":0,"leechers":1,"uploader":"apisto","files":29,"time":1273437285,"description":"VBR EXTREME\nCOVERS INCLUDED\n\n01 - If You Cant Rock Me (3:12)\n02 - Jean Genie (5:33)\n03 - Women In Love (4:24)\n04 - Rock Steady (6:41)\n05 - Rock N Roll Hoochie Koo (7:58)\n06 - The Fool And Me (4:57)\n07 - Keep Playin That Rock N Roll (3:44)\n08 - Eddie &amp; Dave Talking About Recording (1:50)\n09 - Eddie's Warming Up (7:25)\n10 - I'm the One (Show Your Love) (4:30)","torrent":{"xt":"urn:btih:0436c6c8365dfa3134b6234ae195e24945a94662","amp;dn":"Van+Halen+1975-06-13+Pasadena+SOUNDBOARD+COVERS+INCLUDED","amp;tr":["udp%3A%2F%2Ftracker.openbittorrent.com%3A80","udp%3A%2F%2Fopen.demonii.com%3A1337","udp%3A%2F%2Ftracker.coppersurfer.tk%3A6969","udp%3A%2F%2Fexodus.desync.com%3A6969"],"infoHash":"0436c6c8365dfa3134b6234ae195e24945a94662","infoHashBuffer":{"type":"Buffer","data":[4,54,198,200,54,93,250,49,52,182,35,74,225,149,226,73,69,169,70,98]},"announce":[],"urlList":[]}}