{"title":"Mera Gaon Mera Desh 1971 Hindi 2CD DVDRip XviD MP3 [TMB]","uid":8854830,"size":1523815148,"categoryP":"video","categoryS":"movies","magnet":"?xt=urn:btih:0af100192c2c5ab96b372f10a8e703a563401993&amp;dn=Mera+Gaon+Mera+Desh+1971+Hindi+2CD+DVDRip+XviD+MP3+%5BTMB%5D&amp;tr=udp%3A%2F%2Ftracker.openbittorrent.com%3A80&amp;tr=udp%3A%2F%2Fopen.demonii.com%3A1337&amp;tr=udp%3A%2F%2Ftracker.coppersurfer.tk%3A6969&amp;tr=udp%3A%2F%2Fexodus.desync.com%3A6969","seeders":0,"leechers":1,"uploader":"zyx55e","files":2,"time":1377626346,"description":"Mera Gaon Mera Desh 1971 Hindi 2CD DVDRip XviD MP3 [TMB]\n  &lt;a href=&quot;\nhttp://www.imdb.com/title/tt0232081/&quot; rel=&quot;nofollow&quot; target=&quot;_NEW&quot;&gt;\nhttp://www.imdb.com/title/tt0232081/&lt;/a&gt;\n &lt;a href=&quot;\nhttp://en.wikipedia.org/wiki/Mera_Gaon_Mera_Desh&quot; rel=&quot;nofollow&quot; target=&quot;_NEW&quot;&gt;\nhttp://en.wikipedia.org/wiki/Mera_Gaon_Mera_Desh&lt;/a&gt;\n\nLanguage - Hindi\nVideo Codec - XviD\nVideo Container - AVI\nVideo Size - 1.41 GB\nVideo Bitrate - 1316 Kbps\nVideo Resolution - 640 x 480\nVideo Frame Rate - 29.970 fps\nAudio Codec - MP3\nAudio Channels - 2 Channels\nAudio Sampling Rate - 44100 Hz\nAudio Bitrate - 128 Kbps\nMovie Duration - 2 Hours 33 mins\n\nPoster:   &lt;a href=&quot;\nhttp://desibbrg.org/images/71798958754756608953.jpg&quot; rel=&quot;nofollow&quot; target=&quot;_NEW&quot;&gt;\nhttp://desibbrg.org/images/71798958754756608953.jpg&lt;/a&gt;\n\nScreens :   &lt;a href=&quot;\nhttp://desibbrg.org/images/98745522593445832607.png&quot; rel=&quot;nofollow&quot; target=&quot;_NEW&quot;&gt;\nhttp://desibbrg.org/images/98745522593445832607.png&lt;/a&gt;\n &lt;a href=&quot;\nhttp://desibbrg.org/images/57491957982710008626.png&quot; rel=&quot;nofollow&quot; target=&quot;_NEW&quot;&gt;\nhttp://desibbrg.org/images/57491957982710008626.png&lt;/a&gt;\n &lt;a href=&quot;\nhttp://desibbrg.org/images/99887877020553553778.png&quot; rel=&quot;nofollow&quot; target=&quot;_NEW&quot;&gt;\nhttp://desibbrg.org/images/99887877020553553778.png&lt;/a&gt;\n &lt;a href=&quot;\nhttp://desibbrg.org/images/90292137517637323629.png&quot; rel=&quot;nofollow&quot; target=&quot;_NEW&quot;&gt;\nhttp://desibbrg.org/images/90292137517637323629.png&lt;/a&gt;\n &lt;a href=&quot;\nhttp://desibbrg.org/images/71326901756256646747.png&quot; rel=&quot;nofollow&quot; target=&quot;_NEW&quot;&gt;\nhttp://desibbrg.org/images/71326901756256646747.png&lt;/a&gt;\n &lt;a href=&quot;\nhttp://desibbrg.org/images/43251720144300366591.png&quot; rel=&quot;nofollow&quot; target=&quot;_NEW&quot;&gt;\nhttp://desibbrg.org/images/43251720144300366591.png&lt;/a&gt;\n &lt;a href=&quot;\nhttp://desibbrg.org/images/00548128149192731938.png&quot; rel=&quot;nofollow&quot; target=&quot;_NEW&quot;&gt;\nhttp://desibbrg.org/images/00548128149192731938.png&lt;/a&gt;\n &lt;a href=&quot;\nhttp://desibbrg.org/images/21246677842426802199.png&quot; rel=&quot;nofollow&quot; target=&quot;_NEW&quot;&gt;\nhttp://desibbrg.org/images/21246677842426802199.png&lt;/a&gt;\n &lt;a href=&quot;\nhttp://desibbrg.org/images/52522121834247503782.png&quot; rel=&quot;nofollow&quot; target=&quot;_NEW&quot;&gt;\nhttp://desibbrg.org/images/52522121834247503782.png&lt;/a&gt;\n &lt;a href=&quot;\nhttp://desibbrg.org/images/55778341403665168407.png&quot; rel=&quot;nofollow&quot; target=&quot;_NEW&quot;&gt;\nhttp://desibbrg.org/images/55778341403665168407.png&lt;/a&gt;\n\nSample in torrent\n\nIts a release by TMB(The Mumbai Boys). Enjoy it...\n\nExtreme seeding....","torrent":{"xt":"urn:btih:0af100192c2c5ab96b372f10a8e703a563401993","amp;dn":"Mera+Gaon+Mera+Desh+1971+Hindi+2CD+DVDRip+XviD+MP3+%5BTMB%5D","amp;tr":["udp%3A%2F%2Ftracker.openbittorrent.com%3A80","udp%3A%2F%2Fopen.demonii.com%3A1337","udp%3A%2F%2Ftracker.coppersurfer.tk%3A6969","udp%3A%2F%2Fexodus.desync.com%3A6969"],"infoHash":"0af100192c2c5ab96b372f10a8e703a563401993","infoHashBuffer":{"type":"Buffer","data":[10,241,0,25,44,44,90,185,107,55,47,16,168,231,3,165,99,64,25,147]},"announce":[],"urlList":[]}}