{"title":"Remember.Me.2010.720p.BRRip.XviD.AC3-ViSiON","uid":5613126,"size":2935750198,"categoryP":"video","categoryS":"hd___movies","magnet":"?xt=urn:btih:0b5d0a9b515e4cc1f67ca005bb0298ac977e7011&amp;dn=Remember.Me.2010.720p.BRRip.XviD.AC3-ViSiON&amp;tr=udp%3A%2F%2Ftracker.openbittorrent.com%3A80&amp;tr=udp%3A%2F%2Fopen.demonii.com%3A1337&amp;tr=udp%3A%2F%2Ftracker.coppersurfer.tk%3A6969&amp;tr=udp%3A%2F%2Fexodus.desync.com%3A6969","seeders":0,"leechers":1,"uploader":"TvTeam","files":5,"time":1275959444,"description":". \n \n &lt;a href=&quot;\nhttp://www.torrentday.com&quot; rel=&quot;nofollow&quot; target=&quot;_NEW&quot;&gt;\nhttp://www.torrentday.com&lt;/a&gt; :  Your Key To The Scene.\n\n\nNow TvTeam with [No-RAR] Releases.\n\n\n\n(((((((((((((= Enjoy No RAR releases =))))))))))))))))))))\n\n\n\n...................................NFO:....................................\n\n.","torrent":{"xt":"urn:btih:0b5d0a9b515e4cc1f67ca005bb0298ac977e7011","amp;dn":"Remember.Me.2010.720p.BRRip.XviD.AC3-ViSiON","amp;tr":["udp%3A%2F%2Ftracker.openbittorrent.com%3A80","udp%3A%2F%2Fopen.demonii.com%3A1337","udp%3A%2F%2Ftracker.coppersurfer.tk%3A6969","udp%3A%2F%2Fexodus.desync.com%3A6969"],"infoHash":"0b5d0a9b515e4cc1f67ca005bb0298ac977e7011","infoHashBuffer":{"type":"Buffer","data":[11,93,10,155,81,94,76,193,246,124,160,5,187,2,152,172,151,126,112,17]},"announce":[],"urlList":[]}}