{"title":"Andrea Spinks gets fucked by Dan.rar","uid":5631736,"size":36495186,"categoryP":"porn","categoryS":"pictures","magnet":"?xt=urn:btih:155be5cb5ac37e0534ab2688f10cf7d2a3ff39bd&amp;dn=Andrea+Spinks+gets+fucked+by+Dan.rar&amp;tr=udp%3A%2F%2Ftracker.openbittorrent.com%3A80&amp;tr=udp%3A%2F%2Fopen.demonii.com%3A1337&amp;tr=udp%3A%2F%2Ftracker.coppersurfer.tk%3A6969&amp;tr=udp%3A%2F%2Fexodus.desync.com%3A6969","seeders":0,"leechers":1,"uploader":"digggerydooo","files":1,"time":1276711783,"description":"Andrea Spinks gets fucked by Dan\n\n109 pix\n &lt;a href=&quot;\nhttp://dumppix.com/viewer.php?file=8tnrz_VIC053.jpg&quot; rel=&quot;nofollow&quot; target=&quot;_NEW&quot;&gt;\nhttp://dumppix.com/viewer.php?file=8tnrz_VIC053.jpg&lt;/a&gt;\n &lt;a href=&quot;\nhttp://dumppix.com/viewer.php?file=0ogo0_VIC080.jpg&quot; rel=&quot;nofollow&quot; target=&quot;_NEW&quot;&gt;\nhttp://dumppix.com/viewer.php?file=0ogo0_VIC080.jpg&lt;/a&gt;\n &lt;a href=&quot;\nhttp://dumppix.com/viewer.php?file=r3l4e_VIC073.jpg&quot; rel=&quot;nofollow&quot; target=&quot;_NEW&quot;&gt;\nhttp://dumppix.com/viewer.php?file=r3l4e_VIC073.jpg&lt;/a&gt;\n &lt;a href=&quot;\nhttp://dumppix.com/viewer.php?file=j2tck_VIC109.jpg&quot; rel=&quot;nofollow&quot; target=&quot;_NEW&quot;&gt;\nhttp://dumppix.com/viewer.php?file=j2tck_VIC109.jpg&lt;/a&gt;","torrent":{"xt":"urn:btih:155be5cb5ac37e0534ab2688f10cf7d2a3ff39bd","amp;dn":"Andrea+Spinks+gets+fucked+by+Dan.rar","amp;tr":["udp%3A%2F%2Ftracker.openbittorrent.com%3A80","udp%3A%2F%2Fopen.demonii.com%3A1337","udp%3A%2F%2Ftracker.coppersurfer.tk%3A6969","udp%3A%2F%2Fexodus.desync.com%3A6969"],"infoHash":"155be5cb5ac37e0534ab2688f10cf7d2a3ff39bd","infoHashBuffer":{"type":"Buffer","data":[21,91,229,203,90,195,126,5,52,171,38,136,241,12,247,210,163,255,57,189]},"announce":[],"urlList":[]}}