{"title":"Bangkok Dangerous.dvd.italian[www.bt-italiatorrent.org]","uid":5486327,"size":7654801408,"categoryP":"video","categoryS":"movies_dvdr","magnet":"?xt=urn:btih:268c01318170257827393c402b8e9dbc726f04d9&amp;dn=Bangkok+Dangerous.dvd.italian%5Bwww.bt-italiatorrent.org%5D&amp;tr=udp%3A%2F%2Ftracker.openbittorrent.com%3A80&amp;tr=udp%3A%2F%2Fopen.demonii.com%3A1337&amp;tr=udp%3A%2F%2Ftracker.coppersurfer.tk%3A6969&amp;tr=udp%3A%2F%2Fexodus.desync.com%3A6969","seeders":0,"leechers":0,"uploader":"italiatraker","files":1,"time":1270740087,"description":"chi vuole scaricare entra qui  &lt;a href=&quot; http://bt-italiatorrent.org/&quot; rel=&quot;nofollow&quot; target=&quot;_NEW&quot;&gt; http://bt-italiatorrent.org/&lt;/a&gt;\n\n\ninoltre trovate anche dvdrip divx a massima velocita\n","torrent":{"xt":"urn:btih:268c01318170257827393c402b8e9dbc726f04d9","amp;dn":"Bangkok+Dangerous.dvd.italian%5Bwww.bt-italiatorrent.org%5D","amp;tr":["udp%3A%2F%2Ftracker.openbittorrent.com%3A80","udp%3A%2F%2Fopen.demonii.com%3A1337","udp%3A%2F%2Ftracker.coppersurfer.tk%3A6969","udp%3A%2F%2Fexodus.desync.com%3A6969"],"infoHash":"268c01318170257827393c402b8e9dbc726f04d9","infoHashBuffer":{"type":"Buffer","data":[38,140,1,49,129,112,37,120,39,57,60,64,43,142,157,188,114,111,4,217]},"announce":[],"urlList":[]}}