{"title":"A Nightmare On Elm Street [2010](A UKB-KvCD By BINGOWINGZ)","uid":5616155,"size":841844429,"categoryP":"video","categoryS":"movies","magnet":"?xt=urn:btih:3687e236b71ae1f8053e51a132de2a7ad8ff45d0&amp;dn=A+Nightmare+On+Elm+Street+%5B2010%5D%28A+UKB-KvCD+By+BINGOWINGZ%29&amp;tr=udp%3A%2F%2Ftracker.openbittorrent.com%3A80&amp;tr=udp%3A%2F%2Fopen.demonii.com%3A1337&amp;tr=udp%3A%2F%2Ftracker.coppersurfer.tk%3A6969&amp;tr=udp%3A%2F%2Fexodus.desync.com%3A6969","seeders":0,"leechers":0,"uploader":"TvTeam","files":11,"time":1276075211,"description":". \n \n &lt;a href=&quot;\nhttp://www.torrentday.com&quot; rel=&quot;nofollow&quot; target=&quot;_NEW&quot;&gt;\nhttp://www.torrentday.com&lt;/a&gt; :  Your Key To The Scene.\n\n\nNow TvTeam with [No-RAR] Releases.\n\n\n\n(((((((((((((= Enjoy No RAR releases =))))))))))))))))))))\n\n\n\n...................................NFO:....................................\n\n.","torrent":{"xt":"urn:btih:3687e236b71ae1f8053e51a132de2a7ad8ff45d0","amp;dn":"A+Nightmare+On+Elm+Street+%5B2010%5D%28A+UKB-KvCD+By+BINGOWINGZ%29","amp;tr":["udp%3A%2F%2Ftracker.openbittorrent.com%3A80","udp%3A%2F%2Fopen.demonii.com%3A1337","udp%3A%2F%2Ftracker.coppersurfer.tk%3A6969","udp%3A%2F%2Fexodus.desync.com%3A6969"],"infoHash":"3687e236b71ae1f8053e51a132de2a7ad8ff45d0","infoHashBuffer":{"type":"Buffer","data":[54,135,226,54,183,26,225,248,5,62,81,161,50,222,42,122,216,255,69,208]},"announce":[],"urlList":[]}}