{"title":"waterproof-DREAM.mp3","uid":5624527,"size":5353093,"categoryP":"audio","categoryS":"music","magnet":"?xt=urn:btih:3c5b9fba5d23473c9e009f05fc83e5ed458c20a2&amp;dn=waterproof-DREAM.mp3&amp;tr=udp%3A%2F%2Ftracker.openbittorrent.com%3A80&amp;tr=udp%3A%2F%2Fopen.demonii.com%3A1337&amp;tr=udp%3A%2F%2Ftracker.coppersurfer.tk%3A6969&amp;tr=udp%3A%2F%2Fexodus.desync.com%3A6969","seeders":0,"leechers":0,"uploader":"jerrypalsson","files":1,"time":1276428081,"description":"Made by jerry palsson","torrent":{"xt":"urn:btih:3c5b9fba5d23473c9e009f05fc83e5ed458c20a2","amp;dn":"waterproof-DREAM.mp3","amp;tr":["udp%3A%2F%2Ftracker.openbittorrent.com%3A80","udp%3A%2F%2Fopen.demonii.com%3A1337","udp%3A%2F%2Ftracker.coppersurfer.tk%3A6969","udp%3A%2F%2Fexodus.desync.com%3A6969"],"infoHash":"3c5b9fba5d23473c9e009f05fc83e5ed458c20a2","infoHashBuffer":{"type":"Buffer","data":[60,91,159,186,93,35,71,60,158,0,159,5,252,131,229,237,69,140,32,162]},"announce":[],"urlList":[]}}