{"title":"Massimo DaCosta House Music Mix from 5 Magazine","uid":5612869,"size":121527944,"categoryP":"audio","categoryS":"music","magnet":"?xt=urn:btih:52d53c242dfed1df3eace42fb2ce45f4d191212b&amp;dn=Massimo+DaCosta+House+Music+Mix+from+5+Magazine&amp;tr=udp%3A%2F%2Ftracker.openbittorrent.com%3A80&amp;tr=udp%3A%2F%2Fopen.demonii.com%3A1337&amp;tr=udp%3A%2F%2Ftracker.coppersurfer.tk%3A6969&amp;tr=udp%3A%2F%2Fexodus.desync.com%3A6969","seeders":0,"leechers":0,"uploader":"parsonsi","files":-1,"time":1275950106,"description":"New Mix Monday is 5 Magazine's weekly House Music series, featuring the best DJs on the planet. This week we're featuring accomplished producer, DJ and half of the acclaimed Vernon and DaCosta team, Massimo DaCosta. More info at: http://www.5chicago.com/audio\n\nQuality: 256kps mp3\nDate: 7 June 2010\nDuration: 01:03:16\nLink: http://www.5chicago.com/new-mix-monday/massimo-dacosta-060710.html","torrent":{"xt":"urn:btih:52d53c242dfed1df3eace42fb2ce45f4d191212b","amp;dn":"Massimo+DaCosta+House+Music+Mix+from+5+Magazine","amp;tr":["udp%3A%2F%2Ftracker.openbittorrent.com%3A80","udp%3A%2F%2Fopen.demonii.com%3A1337","udp%3A%2F%2Ftracker.coppersurfer.tk%3A6969","udp%3A%2F%2Fexodus.desync.com%3A6969"],"infoHash":"52d53c242dfed1df3eace42fb2ce45f4d191212b","infoHashBuffer":{"type":"Buffer","data":[82,213,60,36,45,254,209,223,62,172,228,47,178,206,69,244,209,145,33,43]},"announce":[],"urlList":[]}}