{"title":"khanacademy.geometry.updated","uid":5541926,"size":453940631,"categoryP":"video","categoryS":"other","magnet":"?xt=urn:btih:611c249bc03af7808f7364672a30003d46e301fd&amp;dn=khanacademy.geometry.updated&amp;tr=udp%3A%2F%2Ftracker.openbittorrent.com%3A80&amp;tr=udp%3A%2F%2Fopen.demonii.com%3A1337&amp;tr=udp%3A%2F%2Ftracker.coppersurfer.tk%3A6969&amp;tr=udp%3A%2F%2Fexodus.desync.com%3A6969","seeders":0,"leechers":1,"uploader":"bdancer","files":23,"time":1273261308,"description":"Complete set of Geometry videos (22 as of 5/7/2010) from http://www.khanacademy.org.  See readme for licensing details.","torrent":{"xt":"urn:btih:611c249bc03af7808f7364672a30003d46e301fd","amp;dn":"khanacademy.geometry.updated","amp;tr":["udp%3A%2F%2Ftracker.openbittorrent.com%3A80","udp%3A%2F%2Fopen.demonii.com%3A1337","udp%3A%2F%2Ftracker.coppersurfer.tk%3A6969","udp%3A%2F%2Fexodus.desync.com%3A6969"],"infoHash":"611c249bc03af7808f7364672a30003d46e301fd","infoHashBuffer":{"type":"Buffer","data":[97,28,36,155,192,58,247,128,143,115,100,103,42,48,0,61,70,227,1,253]},"announce":[],"urlList":[]}}