{"title":"Zemani.11.04.28.Lyuda.Segatura.XXX.IMAGESET-GAGBALL","uid":8857211,"size":104772261,"categoryP":"porn","categoryS":"other","magnet":"?xt=urn:btih:6a9dfea64f4ff8e8dc28416a6e9b3684ba8e92cd&amp;dn=Zemani.11.04.28.Lyuda.Segatura.XXX.IMAGESET-GAGBALL&amp;tr=udp%3A%2F%2Ftracker.openbittorrent.com%3A80&amp;tr=udp%3A%2F%2Fopen.demonii.com%3A1337&amp;tr=udp%3A%2F%2Ftracker.coppersurfer.tk%3A6969&amp;tr=udp%3A%2F%2Fexodus.desync.com%3A6969","seeders":0,"leechers":2,"uploader":"Drarbg","files":106,"time":1377690334,"description":"Zemani.com_11.04.28.Lyuda.Segatura.XXX.IMAGESET-GAGBALL\n","torrent":{"xt":"urn:btih:6a9dfea64f4ff8e8dc28416a6e9b3684ba8e92cd","amp;dn":"Zemani.11.04.28.Lyuda.Segatura.XXX.IMAGESET-GAGBALL","amp;tr":["udp%3A%2F%2Ftracker.openbittorrent.com%3A80","udp%3A%2F%2Fopen.demonii.com%3A1337","udp%3A%2F%2Ftracker.coppersurfer.tk%3A6969","udp%3A%2F%2Fexodus.desync.com%3A6969"],"infoHash":"6a9dfea64f4ff8e8dc28416a6e9b3684ba8e92cd","infoHashBuffer":{"type":"Buffer","data":[106,157,254,166,79,79,248,232,220,40,65,106,110,155,54,132,186,142,146,205]},"announce":[],"urlList":[]}}