{"title":"Diario.Marca.8.junio.2010","uid":5613873,"size":15537903,"categoryP":"other","categoryS":"e_books","magnet":"?xt=urn:btih:8183b4c04d6c01675cd61ad06f9840f5b35f6173&amp;dn=Diario.Marca.8.junio.2010&amp;tr=udp%3A%2F%2Ftracker.openbittorrent.com%3A80&amp;tr=udp%3A%2F%2Fopen.demonii.com%3A1337&amp;tr=udp%3A%2F%2Ftracker.coppersurfer.tk%3A6969&amp;tr=udp%3A%2F%2Fexodus.desync.com%3A6969","seeders":0,"leechers":0,"uploader":"furtaperas","files":1,"time":1275993953,"description":"Diario Deportivo Marca 8 junio 2010","torrent":{"xt":"urn:btih:8183b4c04d6c01675cd61ad06f9840f5b35f6173","amp;dn":"Diario.Marca.8.junio.2010","amp;tr":["udp%3A%2F%2Ftracker.openbittorrent.com%3A80","udp%3A%2F%2Fopen.demonii.com%3A1337","udp%3A%2F%2Ftracker.coppersurfer.tk%3A6969","udp%3A%2F%2Fexodus.desync.com%3A6969"],"infoHash":"8183b4c04d6c01675cd61ad06f9840f5b35f6173","infoHashBuffer":{"type":"Buffer","data":[129,131,180,192,77,108,1,103,92,214,26,208,111,152,64,245,179,95,97,115]},"announce":[],"urlList":[]}}