{"title":"An Office Romance (2010)","uid":5521227,"size":1462729723,"categoryP":"porn","categoryS":"movies","magnet":"?xt=urn:btih:92ea15de1c9935bf6fa89825c53f51dcdec37b46&amp;dn=An+Office+Romance+%282010%29&amp;tr=udp%3A%2F%2Ftracker.openbittorrent.com%3A80&amp;tr=udp%3A%2F%2Fopen.demonii.com%3A1337&amp;tr=udp%3A%2F%2Ftracker.coppersurfer.tk%3A6969&amp;tr=udp%3A%2F%2Fexodus.desync.com%3A6969","seeders":0,"leechers":1,"uploader":"brego45","files":6,"time":1272627405,"description":"Covers\n------------      &lt;a href=&quot;\nhttp://desibbrg.net/imghost/show.php?img=322922_out.phpi322918Cover1.jpg.html&quot; rel=&quot;nofollow&quot; target=&quot;_NEW&quot;&gt;\nhttp://desibbrg.net/imghost/show.php?img=322922_out.phpi322918Cover1.jpg.html&lt;/a&gt; &lt;a href=&quot;\nhttp://desibbrg.net/imghost/show.php?img=322921_out.phpi322917Cover2.jpg.html&quot; rel=&quot;nofollow&quot; target=&quot;_NEW&quot;&gt;\nhttp://desibbrg.net/imghost/show.php?img=322921_out.phpi322917Cover2.jpg.html&lt;/a&gt;\n\nScreenshots\n-----------------      &lt;a href=&quot;\nhttp://desibbrg.net/imghost/show.php?img=322920_out.phpi322916Screens1.jpg.html&quot; rel=&quot;nofollow&quot; target=&quot;_NEW&quot;&gt;\nhttp://desibbrg.net/imghost/show.php?img=322920_out.phpi322916Screens1.jpg.html&lt;/a&gt; &lt;a href=&quot;\nhttp://desibbrg.net/imghost/show.php?img=322919_out.phpi322915Screens2.jpg.html&quot; rel=&quot;nofollow&quot; target=&quot;_NEW&quot;&gt;\nhttp://desibbrg.net/imghost/show.php?img=322919_out.phpi322915Screens2.jpg.html&lt;/a&gt;\n\nCheck out my other 1250+ torrent releases\n----------------------------------------------      &lt;a href=&quot;\nhttp://thepiratebay.se/user/brego45&quot; rel=&quot;nofollow&quot; target=&quot;_NEW&quot;&gt;\nhttp://thepiratebay.se/user/brego45&lt;/a&gt;","torrent":{"xt":"urn:btih:92ea15de1c9935bf6fa89825c53f51dcdec37b46","amp;dn":"An+Office+Romance+%282010%29","amp;tr":["udp%3A%2F%2Ftracker.openbittorrent.com%3A80","udp%3A%2F%2Fopen.demonii.com%3A1337","udp%3A%2F%2Ftracker.coppersurfer.tk%3A6969","udp%3A%2F%2Fexodus.desync.com%3A6969"],"infoHash":"92ea15de1c9935bf6fa89825c53f51dcdec37b46","infoHashBuffer":{"type":"Buffer","data":[146,234,21,222,28,153,53,191,111,168,152,37,197,63,81,220,222,195,123,70]},"announce":[],"urlList":[]}}