{"title":"Teddy Floppy Ear: Mt Adventure v1.2","uid":8731849,"size":360139239,"categoryP":"games","categoryS":"android","magnet":"?xt=urn:btih:9bf95f4b09fd82cdb308510a0c1dc10b1e090474&amp;dn=Teddy+Floppy+Ear%3A+Mt+Adventure+v1.2&amp;tr=udp%3A%2F%2Ftracker.openbittorrent.com%3A80&amp;tr=udp%3A%2F%2Fopen.demonii.com%3A1337&amp;tr=udp%3A%2F%2Ftracker.coppersurfer.tk%3A6969&amp;tr=udp%3A%2F%2Fexodus.desync.com%3A6969","seeders":0,"leechers":2,"uploader":"Androider","files":-1,"time":1374619854,"description":"\nNow you can enjoy Teddy Floppy Ear speaking native Polish language!!\nChoose between Polish and English lectors (in main menu) or subtitles (options menu).\nIn main menu we also added a link to walkthrough that will help you anytime you get stuck. \n\nTeddy Floppy Ear is a main character of series of adventure games for the children based on the famous polish cartoon. Each game mixes entertaining adventure with a healthy dose of learning.\n\nIn &quot;Mountain adventure&quot; episode Teddy visits his uncle, who is a painter living in the mountains.\n\nDuring mountain travels Teddy solves numerous minigames and learns basics of art, color mixing and grading, shape recognition and many more.\nBeautiful hand-painted graphics, soothing music, entertaining and violence free story keep your child occupied for hours.\n\n- Great for even the youngest kids\n- Educational value\n- Absolutely no violence\n- Numerous mini-games for variety\n- Polish or English speaking lector\n- Polish or English subtitles as an option\n\nWhat's New:\n\nAdded polish language lectors.\nAdded polish subtitles.\nAdded a link to walkthrought to help if player got stuck.\n\nMore info:\n &lt;a href=&quot;\nhttps://play.google.com/store/apps/details?id=com.Forever.Uszatek3&quot; rel=&quot;nofollow&quot; target=&quot;_NEW&quot;&gt;\nhttps://play.google.com/store/apps/details?id=com.Forever.Uszatek3&lt;/a&gt;\n\n\nInstructions:\n\n1.Install APK\n2.Copy 'com.Forever.Uszatek3' folder to 'sdcard/Android/Obb'\n3.Launch the game\n","torrent":{"xt":"urn:btih:9bf95f4b09fd82cdb308510a0c1dc10b1e090474","amp;dn":"Teddy+Floppy+Ear%3A+Mt+Adventure+v1.2","amp;tr":["udp%3A%2F%2Ftracker.openbittorrent.com%3A80","udp%3A%2F%2Fopen.demonii.com%3A1337","udp%3A%2F%2Ftracker.coppersurfer.tk%3A6969","udp%3A%2F%2Fexodus.desync.com%3A6969"],"infoHash":"9bf95f4b09fd82cdb308510a0c1dc10b1e090474","infoHashBuffer":{"type":"Buffer","data":[155,249,95,75,9,253,130,205,179,8,81,10,12,29,193,11,30,9,4,116]},"announce":[],"urlList":[]}}