{"title":"Awesome brunette hoe gets her tight cute feet adored","uid":8748349,"size":40478112,"categoryP":"porn","categoryS":"movie_clips","magnet":"?xt=urn:btih:aa7a09cddc3bd71853621060b21aed949c5b1b86&amp;dn=Awesome+brunette+hoe+gets+her+tight+cute+feet+adored&amp;tr=udp%3A%2F%2Ftracker.openbittorrent.com%3A80&amp;tr=udp%3A%2F%2Fopen.demonii.com%3A1337&amp;tr=udp%3A%2F%2Ftracker.coppersurfer.tk%3A6969&amp;tr=udp%3A%2F%2Fexodus.desync.com%3A6969","seeders":0,"leechers":1,"uploader":"pornophil","files":1,"time":1374979860,"description":"Title: Awesome brunette hoe gets her tight cute feet adored\nResolution: 640x480\nDuration: 00:05:17\nSize: 38.6 MB\n\nScreenshot: &lt;a href=&quot;\nhttp://www.picdumper.com/scr/36230c17704ed011c58381303bdaa1e5&quot; rel=&quot;nofollow&quot; target=&quot;_NEW&quot;&gt;\nhttp://www.picdumper.com/scr/36230c17704ed011c58381303bdaa1e5&lt;/a&gt;\n\nPreview index: &lt;a href=&quot;\nhttp://www.picdumper.com/idx/36230c17704ed011c58381303bdaa1e5&quot; rel=&quot;nofollow&quot; target=&quot;_NEW&quot;&gt;\nhttp://www.picdumper.com/idx/36230c17704ed011c58381303bdaa1e5&lt;/a&gt;\n","torrent":{"xt":"urn:btih:aa7a09cddc3bd71853621060b21aed949c5b1b86","amp;dn":"Awesome+brunette+hoe+gets+her+tight+cute+feet+adored","amp;tr":["udp%3A%2F%2Ftracker.openbittorrent.com%3A80","udp%3A%2F%2Fopen.demonii.com%3A1337","udp%3A%2F%2Ftracker.coppersurfer.tk%3A6969","udp%3A%2F%2Fexodus.desync.com%3A6969"],"infoHash":"aa7a09cddc3bd71853621060b21aed949c5b1b86","infoHashBuffer":{"type":"Buffer","data":[170,122,9,205,220,59,215,24,83,98,16,96,178,26,237,148,156,91,27,134]},"announce":[],"urlList":[]}}