{"title":"Ghost.Hunters.Academy.S02E01.HDTV.XviD-OMiCRON","uid":5605491,"size":365909277,"categoryP":"video","categoryS":"tv_shows","magnet":"?xt=urn:btih:b28abb7d0f816f57273b68fb1b7d136391b2b46d&amp;dn=Ghost.Hunters.Academy.S02E01.HDTV.XviD-OMiCRON&amp;tr=udp%3A%2F%2Ftracker.openbittorrent.com%3A80&amp;tr=udp%3A%2F%2Fopen.demonii.com%3A1337&amp;tr=udp%3A%2F%2Ftracker.coppersurfer.tk%3A6969&amp;tr=udp%3A%2F%2Fexodus.desync.com%3A6969","seeders":0,"leechers":2,"uploader":"TvTeam","files":5,"time":1275570019,"description":". \n \n &lt;a href=&quot;\nhttp://www.torrentday.com&quot; rel=&quot;nofollow&quot; target=&quot;_NEW&quot;&gt;\nhttp://www.torrentday.com&lt;/a&gt; :  Your Key To The Scene.\n\n\nNow TvTeam with [No-RAR] Releases.\n\n\n(((((((((((((= Enjoy No RAR releases =))))))))))))))))))))\n\n...................................NFO:....................................\n\n.\n  _|_|    _|      _|  _|    _|_|_|  _|_|_|      _|_|    _|      _|  \n_|    _|  _|_|  _|_|      _|        _|    _|  _|    _|  _|_|    _|  \n_|    _|  _|  _|  _|  _|  _|        _|_|_|    _|    _|  _|  _|  _|  \n_|    _|  _|      _|  _|  _|        _|    _|  _|    _|  _|    _|_|  \n  _|_|    _|      _|  _|    _|_|_|  _|    _|    _|_|    _|      _|  \n\n\n==============-[ OMiCRON PROUDLY PRESENTS ]-==================\nGot something to offer email us at &lt;a class=&quot;__cf_email__&quot; href=&quot;/cdn-cgi/l/email-protection&quot; data-cfemail=&quot;ddb2b0b4beafb2b3beafb8aa9dbab0bcb4b1f3beb2b0&quot;&gt;[email&amp;#160;protected]&lt;/a&gt;&lt;script cf-hash='f9e31' type=&quot;text/javascript&quot;&gt;\n/* &lt;![CDATA[ */!function(){try{var t=&quot;currentScript&quot;in document?document.currentScript:function(){for(var t=document.getElementsByTagName(&quot;script&quot;),e=t.length;e--;)if(t[e].getAttribute(&quot;cf-hash&quot;))return t[e]}();if(t&amp;&amp;t.previousSibling){var e,r,n,i,c=t.previousSibling,a=c.getAttribute(&quot;data-cfemail&quot;);if(a){for(e=&quot;&quot;,r=parseInt(a.substr(0,2),16),n=2;a.length-n;n+=2)i=parseInt(a.substr(n,2),16)^r,e+=String.fromCharCode(i);e=document.createTextNode(e),c.parentNode.replaceChild(e,c)}}}catch(u){}}();/* ]]&gt; */&lt;/script&gt;\nNow Hiring cappers.....\nRelease name: Ghost.Hunters.Academy.S02E01.HDTV.XviD-OMiCRON\nShow Title: Ghost Hunters Academy\nSource: HDTV\nResolution: 624x352\nRelease Date: Jun/03/2010\n========================","torrent":{"xt":"urn:btih:b28abb7d0f816f57273b68fb1b7d136391b2b46d","amp;dn":"Ghost.Hunters.Academy.S02E01.HDTV.XviD-OMiCRON","amp;tr":["udp%3A%2F%2Ftracker.openbittorrent.com%3A80","udp%3A%2F%2Fopen.demonii.com%3A1337","udp%3A%2F%2Ftracker.coppersurfer.tk%3A6969","udp%3A%2F%2Fexodus.desync.com%3A6969"],"infoHash":"b28abb7d0f816f57273b68fb1b7d136391b2b46d","infoHashBuffer":{"type":"Buffer","data":[178,138,187,125,15,129,111,87,39,59,104,251,27,125,19,99,145,178,180,109]},"announce":[],"urlList":[]}}