{"title":"EBOD-301 Onoe Wakaba JAV CENSORED","uid":8805341,"size":1094866790,"categoryP":"porn","categoryS":"movie_clips","magnet":"?xt=urn:btih:b55564e387e2baa840a31067fa8b808135a1f47e&amp;dn=EBOD-301+Onoe+Wakaba+JAV+CENSORED&amp;tr=udp%3A%2F%2Ftracker.openbittorrent.com%3A80&amp;tr=udp%3A%2F%2Fopen.demonii.com%3A1337&amp;tr=udp%3A%2F%2Ftracker.coppersurfer.tk%3A6969&amp;tr=udp%3A%2F%2Fexodus.desync.com%3A6969","seeders":0,"leechers":4,"uploader":"3xplanet","files":1,"time":1376315683,"description":"EBOD-301 Onoe Wakaba JAV CENSORED\nCover &lt;a href=&quot;\nhttp://3xplanet.com/view/6723.1376198046.JPG&quot; rel=&quot;nofollow&quot; target=&quot;_NEW&quot;&gt;\nhttp://3xplanet.com/view/6723.1376198046.JPG&lt;/a&gt;\nScreenshot &lt;a href=&quot;\nhttp://3xplanet.com/view/6748.1376198198.JPG&quot; rel=&quot;nofollow&quot; target=&quot;_NEW&quot;&gt;\nhttp://3xplanet.com/view/6748.1376198198.JPG&lt;/a&gt;\n\nTitle: The super addictive Onoe young leaves in adult Kiss\nStarring: Onoe Wakaba\nStudio: E-BODY\n\nTag: JAV, CENSORED, E-BODY, Big Breasts, lolita, work alone\n\n","torrent":{"xt":"urn:btih:b55564e387e2baa840a31067fa8b808135a1f47e","amp;dn":"EBOD-301+Onoe+Wakaba+JAV+CENSORED","amp;tr":["udp%3A%2F%2Ftracker.openbittorrent.com%3A80","udp%3A%2F%2Fopen.demonii.com%3A1337","udp%3A%2F%2Ftracker.coppersurfer.tk%3A6969","udp%3A%2F%2Fexodus.desync.com%3A6969"],"infoHash":"b55564e387e2baa840a31067fa8b808135a1f47e","infoHashBuffer":{"type":"Buffer","data":[181,85,100,227,135,226,186,168,64,163,16,103,250,139,128,129,53,161,244,126]},"announce":[],"urlList":[]}}