{"title":"Twistys.13.08.16.Ashley.Graham.Get.On.The.Floor.XXX.720p.MP4-KTR","uid":8818324,"size":972398728,"categoryP":"porn","categoryS":"other","magnet":"?xt=urn:btih:b86539d32792aa231f7b2632a2261adb82735190&amp;dn=Twistys.13.08.16.Ashley.Graham.Get.On.The.Floor.XXX.720p.MP4-KTR&amp;tr=udp%3A%2F%2Ftracker.openbittorrent.com%3A80&amp;tr=udp%3A%2F%2Fopen.demonii.com%3A1337&amp;tr=udp%3A%2F%2Ftracker.coppersurfer.tk%3A6969&amp;tr=udp%3A%2F%2Fexodus.desync.com%3A6969","seeders":0,"leechers":1,"uploader":"Drarbg","files":3,"time":1376633958,"description":"Twistys.13.08.16.Ashley.Graham.Get.On.The.Floor.XXX.720p.MP4-KTR\n-----------------------------------------\nScreens : &lt;a href=&quot;\nhttp://imagecurl.org/viewer.php?file=14614481582484664023.jpg&quot; rel=&quot;nofollow&quot; target=&quot;_NEW&quot;&gt;\nhttp://imagecurl.org/viewer.php?file=14614481582484664023.jpg&lt;/a&gt;\n\n","torrent":{"xt":"urn:btih:b86539d32792aa231f7b2632a2261adb82735190","amp;dn":"Twistys.13.08.16.Ashley.Graham.Get.On.The.Floor.XXX.720p.MP4-KTR","amp;tr":["udp%3A%2F%2Ftracker.openbittorrent.com%3A80","udp%3A%2F%2Fopen.demonii.com%3A1337","udp%3A%2F%2Ftracker.coppersurfer.tk%3A6969","udp%3A%2F%2Fexodus.desync.com%3A6969"],"infoHash":"b86539d32792aa231f7b2632a2261adb82735190","infoHashBuffer":{"type":"Buffer","data":[184,101,57,211,39,146,170,35,31,123,38,50,162,38,26,219,130,115,81,144]},"announce":[],"urlList":[]}}