{"title":"Hilton Food Show","uid":5610831,"size":490137762,"categoryP":"video","categoryS":"tv_shows","magnet":"?xt=urn:btih:cc37559cfd0bae1bc7b43abb57d2db376b56ebfb&amp;dn=Hilton+Food+Show&amp;tr=udp%3A%2F%2Ftracker.openbittorrent.com%3A80&amp;tr=udp%3A%2F%2Fopen.demonii.com%3A1337&amp;tr=udp%3A%2F%2Ftracker.coppersurfer.tk%3A6969&amp;tr=udp%3A%2F%2Fexodus.desync.com%3A6969","seeders":0,"leechers":0,"uploader":"TempUsage2010","files":1,"time":1275858398,"description":"Your video","torrent":{"xt":"urn:btih:cc37559cfd0bae1bc7b43abb57d2db376b56ebfb","amp;dn":"Hilton+Food+Show","amp;tr":["udp%3A%2F%2Ftracker.openbittorrent.com%3A80","udp%3A%2F%2Fopen.demonii.com%3A1337","udp%3A%2F%2Ftracker.coppersurfer.tk%3A6969","udp%3A%2F%2Fexodus.desync.com%3A6969"],"infoHash":"cc37559cfd0bae1bc7b43abb57d2db376b56ebfb","infoHashBuffer":{"type":"Buffer","data":[204,55,85,156,253,11,174,27,199,180,58,187,87,210,219,55,107,86,235,251]},"announce":[],"urlList":[]}}