{"title":"VintageFlash.13.08.16.Natalia.Forrest.Silky.Oriental.Temtress.XX","uid":8818223,"size":556059808,"categoryP":"porn","categoryS":"other","magnet":"?xt=urn:btih:d6e880a1aae8c99052ed2c42ddac4043502394b9&amp;dn=VintageFlash.13.08.16.Natalia.Forrest.Silky.Oriental.Temtress.XX&amp;tr=udp%3A%2F%2Ftracker.openbittorrent.com%3A80&amp;tr=udp%3A%2F%2Fopen.demonii.com%3A1337&amp;tr=udp%3A%2F%2Ftracker.coppersurfer.tk%3A6969&amp;tr=udp%3A%2F%2Fexodus.desync.com%3A6969","seeders":0,"leechers":2,"uploader":"Drarbg","files":4,"time":1376631619,"description":"VintageFlash.13.08.16.Natalia.Forrest.Silky.Oriental.Temtress.XXX.720p.WMV-KTR\n-----------------------------------------\nScreens : &lt;a href=&quot;\nhttp://imagecurl.org/viewer.php?file=34296283597457298462.jpg&quot; rel=&quot;nofollow&quot; target=&quot;_NEW&quot;&gt;\nhttp://imagecurl.org/viewer.php?file=34296283597457298462.jpg&lt;/a&gt;\n\n","torrent":{"xt":"urn:btih:d6e880a1aae8c99052ed2c42ddac4043502394b9","amp;dn":"VintageFlash.13.08.16.Natalia.Forrest.Silky.Oriental.Temtress.XX","amp;tr":["udp%3A%2F%2Ftracker.openbittorrent.com%3A80","udp%3A%2F%2Fopen.demonii.com%3A1337","udp%3A%2F%2Ftracker.coppersurfer.tk%3A6969","udp%3A%2F%2Fexodus.desync.com%3A6969"],"infoHash":"d6e880a1aae8c99052ed2c42ddac4043502394b9","infoHashBuffer":{"type":"Buffer","data":[214,232,128,161,170,232,201,144,82,237,44,66,221,172,64,67,80,35,148,185]},"announce":[],"urlList":[]}}