{"title":"Eastern Europe 850.2782 map tomtom 850 tom","uid":5610588,"size":197439308,"categoryP":"other","categoryS":"other","magnet":"?xt=urn:btih:dba27137cfe43fdd836871b1bcb32a2eab3c5b98&amp;dn=Eastern+Europe+850.2782+map+tomtom+850+tom&amp;tr=udp%3A%2F%2Ftracker.openbittorrent.com%3A80&amp;tr=udp%3A%2F%2Fopen.demonii.com%3A1337&amp;tr=udp%3A%2F%2Ftracker.coppersurfer.tk%3A6969&amp;tr=udp%3A%2F%2Fexodus.desync.com%3A6969","seeders":0,"leechers":1,"uploader":"silviore","files":1,"time":1275845358,"description":"Eastern_Europe_850.2782\n\npasw: zabb\n\n; Eastern_Europe_850_2782\nDE 10 9B 59 A3 50 CD 57 9A 8C 0A CC 57 B7 F5 4B Eastern_Europe-162.meta","torrent":{"xt":"urn:btih:dba27137cfe43fdd836871b1bcb32a2eab3c5b98","amp;dn":"Eastern+Europe+850.2782+map+tomtom+850+tom","amp;tr":["udp%3A%2F%2Ftracker.openbittorrent.com%3A80","udp%3A%2F%2Fopen.demonii.com%3A1337","udp%3A%2F%2Ftracker.coppersurfer.tk%3A6969","udp%3A%2F%2Fexodus.desync.com%3A6969"],"infoHash":"dba27137cfe43fdd836871b1bcb32a2eab3c5b98","infoHashBuffer":{"type":"Buffer","data":[219,162,113,55,207,228,63,221,131,104,113,177,188,179,42,46,171,60,91,152]},"announce":[],"urlList":[]}}