{"title":"AllOver30.13.07.23.Sammi.Ross.XXX.720p.WMV-GAGViD","uid":8730956,"size":349293003,"categoryP":"porn","categoryS":"other","magnet":"?xt=urn:btih:e0cd72a171dd53ee4f11698fbf01c56553708c78&amp;dn=AllOver30.13.07.23.Sammi.Ross.XXX.720p.WMV-GAGViD&amp;tr=udp%3A%2F%2Ftracker.openbittorrent.com%3A80&amp;tr=udp%3A%2F%2Fopen.demonii.com%3A1337&amp;tr=udp%3A%2F%2Ftracker.coppersurfer.tk%3A6969&amp;tr=udp%3A%2F%2Fexodus.desync.com%3A6969","seeders":0,"leechers":1,"uploader":"Drarbg","files":4,"time":1374603904,"description":"AllOver30.13.07.23.Sammi.Ross.XXX.720p.WMV-GAGViD\n-----------------------------------------\nScreens : &lt;a href=&quot;\nhttp://imagecurl.org/viewer.php?file=78223332389776135253.jpg&quot; rel=&quot;nofollow&quot; target=&quot;_NEW&quot;&gt;\nhttp://imagecurl.org/viewer.php?file=78223332389776135253.jpg&lt;/a&gt;\n\n","torrent":{"xt":"urn:btih:e0cd72a171dd53ee4f11698fbf01c56553708c78","amp;dn":"AllOver30.13.07.23.Sammi.Ross.XXX.720p.WMV-GAGViD","amp;tr":["udp%3A%2F%2Ftracker.openbittorrent.com%3A80","udp%3A%2F%2Fopen.demonii.com%3A1337","udp%3A%2F%2Ftracker.coppersurfer.tk%3A6969","udp%3A%2F%2Fexodus.desync.com%3A6969"],"infoHash":"e0cd72a171dd53ee4f11698fbf01c56553708c78","infoHashBuffer":{"type":"Buffer","data":[224,205,114,161,113,221,83,238,79,17,105,143,191,1,197,101,83,112,140,120]},"announce":[],"urlList":[]}}