{"title":"Pretty Little Latinas 27 - 2004 DVDRip","uid":8730337,"size":1738509859,"categoryP":"porn","categoryS":"movies","magnet":"?xt=urn:btih:ec685fd301a0cd2e80ef4e6987ccd4a4ec828964&amp;dn=Pretty+Little+Latinas+27+-+2004+DVDRip&amp;tr=udp%3A%2F%2Ftracker.openbittorrent.com%3A80&amp;tr=udp%3A%2F%2Fopen.demonii.com%3A1337&amp;tr=udp%3A%2F%2Ftracker.coppersurfer.tk%3A6969&amp;tr=udp%3A%2F%2Fexodus.desync.com%3A6969","seeders":0,"leechers":1,"uploader":null,"files":1,"time":1374590027,"description":"screens ---\n\n &lt;a href=&quot;\nhttp://imghorny.biz/share-0225_51EE762A.html&quot; rel=&quot;nofollow&quot; target=&quot;_NEW&quot;&gt;\nhttp://imghorny.biz/share-0225_51EE762A.html&lt;/a&gt;\n\n &lt;a href=&quot;\nhttp://imghorny.biz/share-671D_51EE7645.html&quot; rel=&quot;nofollow&quot; target=&quot;_NEW&quot;&gt;\nhttp://imghorny.biz/share-671D_51EE7645.html&lt;/a&gt;","torrent":{"xt":"urn:btih:ec685fd301a0cd2e80ef4e6987ccd4a4ec828964","amp;dn":"Pretty+Little+Latinas+27+-+2004+DVDRip","amp;tr":["udp%3A%2F%2Ftracker.openbittorrent.com%3A80","udp%3A%2F%2Fopen.demonii.com%3A1337","udp%3A%2F%2Ftracker.coppersurfer.tk%3A6969","udp%3A%2F%2Fexodus.desync.com%3A6969"],"infoHash":"ec685fd301a0cd2e80ef4e6987ccd4a4ec828964","infoHashBuffer":{"type":"Buffer","data":[236,104,95,211,1,160,205,46,128,239,78,105,135,204,212,164,236,130,137,100]},"announce":[],"urlList":[]}}