{"title":"Beautiful outdoor Fuck","uid":8725307,"size":348766971,"categoryP":"porn","categoryS":"movie_clips","magnet":"?xt=urn:btih:fc23d63b6f5f75ae499f10afc54df44adbb0f2e8&amp;dn=Beautiful+outdoor+Fuck&amp;tr=udp%3A%2F%2Ftracker.openbittorrent.com%3A80&amp;tr=udp%3A%2F%2Fopen.demonii.com%3A1337&amp;tr=udp%3A%2F%2Ftracker.coppersurfer.tk%3A6969&amp;tr=udp%3A%2F%2Fexodus.desync.com%3A6969","seeders":0,"leechers":0,"uploader":"expressfile","files":1,"time":1374506728,"description":"Beautiful outdoor Fuck\n &lt;a href=&quot;\nhttp://bestgirls.info/?v=LKNFa.jpg&quot; rel=&quot;nofollow&quot; target=&quot;_NEW&quot;&gt;\nhttp://bestgirls.info/?v=LKNFa.jpg&lt;/a&gt;\n &lt;a href=&quot;\nhttp://bestgirls.info/?v=RzVtD.jpg&quot; rel=&quot;nofollow&quot; target=&quot;_NEW&quot;&gt;\nhttp://bestgirls.info/?v=RzVtD.jpg&lt;/a&gt;\n\nFile: mp4\nSize: 348766971 bytes (332.61 MiB), duration: 00:21:34, avg.bitrate: 2156 kb/s\nAudio: aac, 44100 Hz, stereo (und)\nVideo: mpeg4, yuv420p, 854x480, 25.00 fps(r)\n\nPlease seed and enjoy\n\nCheck all my torrents\n &lt;a href=&quot;\nhttp://thepiratebay.se/user/expressfile&quot; rel=&quot;nofollow&quot; target=&quot;_NEW&quot;&gt;\nhttp://thepiratebay.se/user/expressfile&lt;/a&gt;","torrent":{"xt":"urn:btih:fc23d63b6f5f75ae499f10afc54df44adbb0f2e8","amp;dn":"Beautiful+outdoor+Fuck","amp;tr":["udp%3A%2F%2Ftracker.openbittorrent.com%3A80","udp%3A%2F%2Fopen.demonii.com%3A1337","udp%3A%2F%2Ftracker.coppersurfer.tk%3A6969","udp%3A%2F%2Fexodus.desync.com%3A6969"],"infoHash":"fc23d63b6f5f75ae499f10afc54df44adbb0f2e8","infoHashBuffer":{"type":"Buffer","data":[252,35,214,59,111,95,117,174,73,159,16,175,197,77,244,74,219,176,242,232]},"announce":[],"urlList":[]}}